{
  "actions.backToHomepage": {
    "message": "Back to homepage"
  },
  "actions.copyShareUrl": {
    "message": "Copy URL"
  },
  "actions.download": {
    "message": "Download"
  },
  "actions.loadMore": {
    "message": "Load more"
  },
  "actions.privacyRequests": {
    "message": "Fortrolighedsanmodninger"
  },
  "actions.reload": {
    "message": "Reload"
  },
  "actions.share": {
    "message": "Share:"
  },
  "actions.startUsingCookies": {
    "message": "Begynd at bruge cookies"
  },
  "actions.stopUsingCookies": {
    "message": "Stop med at bruge cookies"
  },
  "actions.subscribe": {
    "message": "Tilmeld"
  },
  "actions.unsubscribe": {
    "message": "Frameld"
  },
  "boilerplate.title": {
    "message": "Om {companyName}"
  },
  "categories.title": {
    "message": "Categories"
  },
  "contacts.title": {
    "message": "Kontakt"
  },
  "errors.emailInvalid": {
    "message": "Opgiv en gyldig e-mailadresse"
  },
  "errors.fieldRequired": {
    "message": "Dette felt er obligatorisk"
  },
  "errors.unknown": {
    "message": "Noget gik galt. Prøv at indsende formularen igen"
  },
  "mediaGallery.title": {
    "message": "Mediegalleri"
  },
  "noStories.subtitle": {
    "message": "Come back later to see new stories."
  },
  "noStories.title": {
    "message": "Welcome to {newsroom}!"
  },
  "notFound.subtitle": {
    "message": "If you typed the URL yourself, check the spelling in the address bar."
  },
  "notFound.title": {
    "message": "The page you’re looking for doesn’t exist..."
  },
  "serverError.subtitle": {
    "message": "Try refreshing the page or coming back a bit later."
  },
  "serverError.title": {
    "message": "Noget er gået galt..."
  },
  "subscription.captchaDisclaimer": {
    "description": "The variables are replaced with links containing text from `subscription.privacyPolicy` and `subscription.termsOfService` messages respectively",
    "message": "Dette websted er beskyttet af hCaptcha, og dets {privacyPolicyLink} og {termsOfServiceLink} gælder."
  },
  "subscription.formTitle": {
    "message": "Få opdateringer i din indbakke"
  },
  "subscription.labelEmail": {
    "message": "Din e-mail-adresse"
  },
  "subscription.privacyPolicy": {
    "message": "Privatlivspolitik"
  },
  "subscription.termsOfService": {
    "message": "Servicevilkår"
  }
}
