{
  "actions.backToHomepage": {
    "message": "Takaisin kotisivulle"
  },
  "actions.copyShareUrl": {
    "message": "Kopioi URL"
  },
  "actions.download": {
    "message": "Lataa"
  },
  "actions.loadMore": {
    "message": "Lataa lisää"
  },
  "actions.privacyRequests": {
    "message": "Tietosuojapyynnöt"
  },
  "actions.reload": {
    "message": "Lataa uudelleen"
  },
  "actions.share": {
    "message": "Jaa:"
  },
  "actions.startUsingCookies": {
    "message": "Aloita evästeiden käyttö"
  },
  "actions.stopUsingCookies": {
    "message": "Lopeta evästeiden käyttö"
  },
  "actions.subscribe": {
    "message": "Tilaa"
  },
  "actions.unsubscribe": {
    "message": "Peru tilaus"
  },
  "boilerplate.contact": {
    "message": "Ota yhteyttä"
  },
  "boilerplate.title": {
    "message": "Tietoja yrityksestä {companyName}"
  },
  "categories.title": {
    "message": "Kategoriat"
  },
  "contacts.title": {
    "message": "Contact us"
  },
  "cookieConsent.accept": {
    "message": "Kyllä, voitte käyttää evästeitä"
  },
  "cookieConsent.notice": {
    "message": "Voit peruuttaa evästeet milloin tahansa sivun alalaidasta."
  },
  "cookieConsent.reject": {
    "message": "Ei, älkää käyttäkö evästeitä"
  },
  "cookieConsent.subtitle": {
    "message": "Käytämme sivustollamme evästeitä. Niiden avulla tutustumme sinuun ja tapoihisi käyttää sivustoa. Näin pystymme tarjoamaan arvokkaamman ja yksilöllisemmän kokemuksen sinulle ja muille käyttäjille."
  },
  "cookieConsent.title": {
    "message": "Käyttäisimme mielellämme evästeitä"
  },
  "errors.emailInvalid": {
    "message": "Syötä voimassaoleva sähköpostiosoite"
  },
  "errors.fieldRequired": {
    "message": "Tämä kenttä on pakollinen"
  },
  "errors.unknown": {
    "message": "Jotain meni pieleen. Yritä lähettää lomake uudelleen"
  },
  "mediaGallery.title": {
    "message": "Mediagalleria"
  },
  "misc.embargoMessage": {
    "description": "Embargo means that the story is not allowed to be shared before the specified date",
    "message": "Embargo until {date}"
  },
  "misc.loading": {
    "message": "Loading..."
  },
  "misc.shareUrlCopied": {
    "message": "URL copied!"
  },
  "misc.toggleMobileNavigation": {
    "description": "A tooltip for a button that toggles the mobile menu on the web page",
    "message": "Toggle navigation"
  },
  "noStories.subtitle": {
    "message": "Palaa takaisin myöhemmin nähdäksesi uusia tarinoita."
  },
  "noStories.title": {
    "message": "Tervetuloa {newsroom}!"
  },
  "notFound.subtitle": {
    "message": "Jos kirjoitit URL-osoitteen itse, tarkista oikeinkirjoitus osoitepalkista."
  },
  "notFound.title": {
    "message": "Etsimääsi sivua ei ole olemassa..."
  },
  "serverError.subtitle": {
    "message": "Yritä päivittää sivu tai palaa takaisin myöhemmin."
  },
  "serverError.title": {
    "message": "Jokin meni vikaan..."
  },
  "subscription.captchaDisclaimer": {
    "description": "The variables are replaced with links containing text from `subscription.privacyPolicy` and `subscription.termsOfService` messages respectively",
    "message": "Sivusto on suojattu hCaptchalla ja sen {privacyPolicyLink} sekä {termsOfServiceLink} ovat voimassa."
  },
  "subscription.formTitle": {
    "message": "Ota vastaan päivityksiä sähköpostiisi"
  },
  "subscription.labelEmail": {
    "message": "Sähköpostiosoitteesi"
  },
  "subscription.privacyPolicy": {
    "message": "Tietosuojakäytännöt"
  },
  "subscription.termsOfService": {
    "message": "Käyttöehdot"
  }
}
